prevision/__init__.py
prevision/main.py
prevision/cli/__init__.py
prevision/cli/cli.py
prevision/config/__init__.py
prevision/config/config.py
prevision/config/validate.py
prevision/core/__init__.py
prevision/core/evaluation_strategy.py
prevision/core/prule.py
prevision/core/ptrs.py
prevision/core/ptrs_comp_tree_data.py
prevision/core/rose_tree.py
prevision/core/rose_tree_converter.py
prevision/core/term.py
prevision/core/parse/__init__.py
prevision/core/parse/ari.py
prevision/core/parse/parse_ptrs.py
prevision/core/parse/parse_trs.py
prevision/core/parse/utility.py
prevision-0.0.1.dist-info/METADATA
prevision-0.0.1.dist-info/WHEEL
prevision-0.0.1.dist-info/entry_points.txt
prevision-0.0.1.dist-info/licenses/LICENSE
prevision-0.0.1.dist-info/RECORD
