Metadata-Version: 2.4
Name: prevision
Version: 0.0.1
Summary: A Visualization Tool for Computations of Probabilistic Term Rewriting
Author-email: David Weber <david.pascal.weber@example.com>
License: MIT License
License-File: LICENSE
Classifier: License :: OSI Approved :: MIT License
Classifier: Operating System :: OS Independent
Classifier: Programming Language :: Python :: 3
Requires-Python: >=3.12
Requires-Dist: graphviz==0.20.3
Requires-Dist: pydot==3.0.4
